{
  "metadata": {
    "key_fields": [
      "mach",
      "beta",
      "sweep_angle"
    ],
    "value_fields": [
      "fpp_wall",
      "gcfp_wall",
      "g_wall"
    ],
    "entries_count": 15
  },
  "entries": [
    {
      "mach": 2.0,
      "beta": 0.0,
      "sweep_angle": 0.0,
      "fpp_wall": 0.514613982513351,
      "gcfp_wall": 4.620653353826221e-06,
      "g_wall": 1.676145627863315
    },
    {
      "mach": 2.0,
      "beta": 0.0,
      "sweep_angle": 45.0,
      "fpp_wall": 0.5146137329399676,
      "gcfp_wall": 0.5146134542302174,
      "g_wall": 1.676144058286491
    },
    {
      "mach": 2.0,
      "beta": 0.1818,
      "sweep_angle": 45.0,
      "fpp_wall": 0.7311003900882437,
      "gcfp_wall": 0.5268091453743418,
      "g_wall": 1.6740758288475914
    },
    {
      "mach": 2.5,
      "beta": 0.1818,
      "sweep_angle": 45.0,
      "fpp_wall": 0.7615632830189506,
      "gcfp_wall": 0.5415766581998837,
      "g_wall": 2.05190694406622
    },
    {
      "mach": 3.0,
      "beta": 0.1818,
      "sweep_angle": 45.0,
      "fpp_wall": 0.7952204786676693,
      "gcfp_wall": 0.5594922218809307,
      "g_wall": 2.5125553183396483
    },
    {
      "mach": 3.5,
      "beta": 0.1818,
      "sweep_angle": 45.0,
      "fpp_wall": 0.8307801789174126,
      "gcfp_wall": 0.5796938297329728,
      "g_wall": 3.0556586010178193
    },
    {
      "mach": 4.0,
      "beta": 0.1818,
      "sweep_angle": 45.0,
      "fpp_wall": 0.8673183568353868,
      "gcfp_wall": 0.6014681598690961,
      "g_wall": 3.6808425626863497
    },
    {
      "mach": 4.5,
      "beta": 0.1818,
      "sweep_angle": 45.0,
      "fpp_wall": 0.9041881954136817,
      "gcfp_wall": 0.6242411815943968,
      "g_wall": 4.387830947911565
    },
    {
      "mach": 5.0,
      "beta": 0.1818,
      "sweep_angle": 45.0,
      "fpp_wall": 0.9409698582699668,
      "gcfp_wall": 0.6475798551248412,
      "g_wall": 5.176418147768516
    },
    {
      "mach": 5.5,
      "beta": 0.1818,
      "sweep_angle": 45.0,
      "fpp_wall": 0.9773887830439149,
      "gcfp_wall": 0.6711721431851653,
      "g_wall": 6.046437792670425
    },
    {
      "mach": 6.0,
      "beta": 0.1818,
      "sweep_angle": 45.0,
      "fpp_wall": 1.0132631771262939,
      "gcfp_wall": 0.69479170688977,
      "g_wall": 6.997745684009225
    },
    {
      "mach": 6.5,
      "beta": 0.1818,
      "sweep_angle": 45.0,
      "fpp_wall": 1.0485103188147513,
      "gcfp_wall": 0.7182873442621799,
      "g_wall": 8.030414860288504
    },
    {
      "mach": 7.0,
      "beta": 0.1818,
      "sweep_angle": 45.0,
      "fpp_wall": 1.083058832784431,
      "gcfp_wall": 0.7415585432541922,
      "g_wall": 9.144169576370754
    },
    {
      "mach": 7.5,
      "beta": 0.1818,
      "sweep_angle": 45.0,
      "fpp_wall": 1.1169033080123296,
      "gcfp_wall": 0.764538590272112,
      "g_wall": 10.339078582100573
    },
    {
      "mach": 8.0,
      "beta": 0.1818,
      "sweep_angle": 45.0,
      "fpp_wall": 1.1500324666300192,
      "gcfp_wall": 0.7871739037510288,
      "g_wall": 11.615197452956943
    }
  ]
}